dpack/__init__.py
dpack/__main__.py
dpack/base.py
dpack/cli.py
dpack/finders.py
dpack/serve.py
dpack/processors/__init__.py
dpack/processors/cssmin.py
dpack/processors/jsmin.py
dpack/processors/rewrite.py
dpack/processors/sass.py
dpack-0.5.0.dist-info/METADATA
dpack-0.5.0.dist-info/WHEEL
dpack-0.5.0.dist-info/entry_points.txt
dpack-0.5.0.dist-info/licenses/LICENSE
dpack-0.5.0.dist-info/RECORD
