Metadata-Version: 2.4
Name: dpack
Version: 0.5.0
Summary: Asset packager for Django.
Author-email: Dan Watson <dcwatson@gmail.com>
License: MIT
License-File: LICENSE
Classifier: Development Status :: 3 - Alpha
Classifier: Intended Audience :: Developers
Classifier: License :: OSI Approved :: MIT License
Classifier: Programming Language :: Python
Classifier: Programming Language :: Python :: 3
Requires-Python: >=3.9
Requires-Dist: pyyaml>=6.0.2
Provides-Extra: all
Requires-Dist: libsass; extra == 'all'
Requires-Dist: rcssmin; extra == 'all'
Requires-Dist: rjsmin; extra == 'all'
Provides-Extra: cssmin
Requires-Dist: rcssmin; extra == 'cssmin'
Provides-Extra: jsmin
Requires-Dist: rjsmin; extra == 'jsmin'
Provides-Extra: sass
Requires-Dist: libsass; extra == 'sass'
